LICENSE
MANIFEST.in
README.md
setup.py
pose_trigger.egg-info/PKG-INFO
pose_trigger.egg-info/SOURCES.txt
pose_trigger.egg-info/dependency_links.txt
pose_trigger.egg-info/entry_points.txt
pose_trigger.egg-info/requires.txt
pose_trigger.egg-info/top_level.txt
posetrigger/__init__.py
posetrigger/__main__.py
posetrigger/acquisition.py
posetrigger/acquisition_control.py
posetrigger/camera_interface.py
posetrigger/evaluation.py
posetrigger/evaluation_control.py
posetrigger/expression.py
posetrigger/frame_view.py
posetrigger/main_widget.py
posetrigger/preprocessing_control.py
posetrigger/service.py
posetrigger/storage_control.py
posetrigger/trigger.py
posetrigger/trigger_control.py
posetrigger/bin/FastEventServer_linux_x86_64