Metadata-Version: 2.1
Name: pose-trigger
Version: 1.1.1
Summary: a python application for real-time, closed-loop application of TTL trigger generation based on the pose of the subject
Home-page: https://github.com/gwappa/python-labvideocapture
Author: Keisuke Sehara
Author-email: keisuke.sehara@gmail.com
License: MIT
Platform: UNKNOWN
Classifier: Development Status :: 3 - Alpha
Classifier: License :: OSI Approved :: MIT License
Classifier: Programming Language :: Python :: 3
Classifier: Intended Audience :: Science/Research
Requires-Python: >=3.7
Provides-Extra: dlc
